<?xml version="1.0" encoding="utf-8" standalone="no"?>
<billStatus>
  <version>3.0.0</version>
  <bill>
    <number>4514</number>
    <updateDate>2022-12-29T18:33:46Z</updateDate>
    <updateDateIncludingText>2022-12-29T18:33:46Z</updateDateIncludingText>
    <originChamber>Senate</originChamber>
    <type>S</type>
    <introducedDate>2022-07-13</introducedDate>
    <congress>117</congress>
    <committees>
      <item>
        <systemCode>ssfr00</systemCode>
        <name>Foreign Relations Committee</name>
        <chamber>Senate</chamber>
        <type>Standing</type>
        <activities>
          <item>
            <name>Referred to</name>
            <date>2022-07-13T16:09:52Z</date>
          </item>
        </activities>
      </item>
    </committees>
    <actions>
      <item>
        <actionDate>2022-07-13</actionDate>
        <committees>
          <item>
            <systemCode>ssfr00</systemCode>
            <name>Foreign Relations Committee</name>
          </item>
        </committees>
        <sourceSystem>
          <name>Senate</name>
        </sourceSystem>
        <text>Read twice and referred to the Committee on Foreign Relations.</text>
        <type>IntroReferral</type>
      </item>
      <item>
        <actionDate>2022-07-13</actionDate>
        <text>Introduced in Senate</text>
        <type>IntroReferral</type>
        <actionCode>10000</actionCode>
        <sourceSystem>
          <code>9</code>
          <name>Library of Congress</name>
        </sourceSystem>
      </item>
    </actions>
    <sponsors>
      <item>
        <bioguideId>Y000064</bioguideId>
        <fullName>Sen. Young, Todd [R-IN]</fullName>
        <firstName>Todd</firstName>
        <lastName>Young</lastName>
        <party>R</party>
        <state>IN</state>
        <identifiers>
          <bioguideId>Y000064</bioguideId>
        </identifiers>
        <middleName>C.</middleName>
        <isByRequest>N</isByRequest>
      </item>
    </sponsors>
    <cosponsors>
      <item>
        <bioguideId>C001088</bioguideId>
        <fullName>Sen. Coons, Christopher A. [D-DE]</fullName>
        <firstName>Christopher</firstName>
        <lastName>Coons</lastName>
        <party>D</party>
        <state>DE</state>
        <identifiers>
          <bioguideId>C001088</bioguideId>
        </identifiers>
        <middleName>A.</middleName>
        <sponsorshipDate>2022-07-13</sponsorshipDate>
        <isOriginalCosponsor>True</isOriginalCosponsor>
      </item>
      <item>
        <bioguideId>D000563</bioguideId>
        <fullName>Sen. Durbin, Richard J. [D-IL]</fullName>
        <firstName>Richard</firstName>
        <lastName>Durbin</lastName>
        <party>D</party>
        <state>IL</state>
        <identifiers>
          <bioguideId>D000563</bioguideId>
        </identifiers>
        <middleName>J.</middleName>
        <sponsorshipDate>2022-07-27</sponsorshipDate>
        <isOriginalCosponsor>False</isOriginalCosponsor>
      </item>
      <item>
        <bioguideId>S001198</bioguideId>
        <fullName>Sen. Sullivan, Dan [R-AK]</fullName>
        <firstName>Dan</firstName>
        <lastName>Sullivan</lastName>
        <party>R</party>
        <state>AK</state>
        <identifiers>
          <bioguideId>S001198</bioguideId>
        </identifiers>
        <sponsorshipDate>2022-07-27</sponsorshipDate>
        <isOriginalCosponsor>False</isOriginalCosponsor>
      </item>
    </cosponsors>
    <policyArea>
      <name>Foreign Trade and International Finance</name>
    </policyArea>
    <subjects>
      <legislativeSubjects/>
      <policyArea>
        <name>Foreign Trade and International Finance</name>
      </policyArea>
    </subjects>
    <summaries>
      <summary>
        <versionCode>00</versionCode>
        <actionDate>2022-07-13</actionDate>
        <actionDesc>Introduced in Senate</actionDesc>
        <updateDate>2022-09-20T21:28:43Z</updateDate>
        <text>
          <![CDATA[ <p><strong>Countering Economic Coercion Act of 2022</strong></p> <p>This bill authorizes the President to take certain actions to assist foreign trading partners affected by economic coercion. <em>Economic coercion</em> refers to actions or threats undertaken by a foreign adversary to restrain, obstruct, or manipulate trade, foreign aid, investment, or commerce with the intent to cause economic harm or influence sovereign political actions.</p> <p>Specifically, the bill authorizes the President (upon a determination that a foreign trading partner is subject to economic coercion) to exercise specified authorities to support or assist the foreign trading partner. These authorities include, among others, decreasing duties or modifying tariff-rate quotas on imports from the foreign trading partner, requesting appropriations for foreign aid, and expediting export licensing decisions and regulatory processes.</p> <p>The President must consult with Congress prior to exercising any authority. Additionally, the President must publish notice in the Federal Register related to the exercise of such authority.</p> <p>Any determination of economic coercion must be revoked at the earliest of (1) two years from the date of determination, (2) upon a joint resolution of Congress, or (3) when the President revokes the determination. </p> <p>The bill also directs the President to endeavor to coordinate with other foreign trading partners to broaden economic support for the foreign trading partner.</p>]]>
        </text>
      </summary>
    </summaries>
    <title>Countering Economic Coercion Act of 2022</title>
    <titles>
      <item>
        <titleType>Display Title</titleType>
        <title>Countering Economic Coercion Act of 2022</title>
      </item>
      <item>
        <titleType>Short Title(s) as Introduced</titleType>
        <title>Countering Economic Coercion Act of 2022</title>
        <billTextVersionName>Introduced in Senate</billTextVersionName>
        <billTextVersionCode>IS</billTextVersionCode>
      </item>
      <item>
        <titleType>Official Title as Introduced</titleType>
        <title>A bill to grant certain authorities to the President to combat economic coercion by foreign adversaries, and for other purposes.</title>
        <billTextVersionName>Introduced in Senate</billTextVersionName>
        <billTextVersionCode>IS</billTextVersionCode>
      </item>
    </titles>
    <textVersions>
      <item>
        <type>Introduced in Senate</type>
        <date>2022-07-13T04:00:00Z</date>
        <formats>
          <item>
            <url>https://www.govinfo.gov/content/pkg/BILLS-117s4514is/xml/BILLS-117s4514is.xml</url>
          </item>
        </formats>
      </item>
      <item>
        <date/>
        <formats/>
        <type/>
      </item>
    </textVersions>
    <latestAction>
      <actionDate>2022-07-13</actionDate>
      <text>Read twice and referred to the Committee on Foreign Relations.</text>
    </latestAction>
  </bill>
  <dublinCore xmlns:dc="http://purl.org/dc/elements/1.1/">
    <dc:format>text/xml</dc:format>
    <dc:language>EN</dc:language>
    <dc:rights>Pursuant to Title 17 Section 105 of the United States Code, this file is not subject to copyright protection and is in the public domain.</dc:rights>
    <dc:contributor>Congressional Research Service, Library of Congress</dc:contributor>
    <dc:description>This file contains bill summaries and statuses for federal legislation. A bill summary describes the most significant provisions of a piece of legislation and details the effects the legislative text may have on current law and federal programs. Bill summaries are authored by the Congressional Research Service (CRS) of the Library of Congress. As stated in Public Law 91-510 (2 USC 166 (d)(6)), one of the duties of CRS is "to prepare summaries and digests of bills and resolutions of a public general nature introduced in the Senate or House of Representatives". For more information, refer to the User Guide that accompanies this file.</dc:description>
  </dublinCore>
</billStatus>
