<?xml version="1.0" encoding="utf-8" standalone="no"?>
<billStatus>
  <version>3.0.0</version>
  <bill>
    <number>3428</number>
    <updateDate>2022-12-31T10:35:41Z</updateDate>
    <updateDateIncludingText>2022-12-31T10:35:41Z</updateDateIncludingText>
    <originChamber>House</originChamber>
    <type>HR</type>
    <introducedDate>2021-05-20</introducedDate>
    <congress>117</congress>
    <constitutionalAuthorityStatementText>
      <![CDATA[<pre>[Congressional Record Volume 167, Number 88 (Thursday, May 20, 2021)][House]From the Congressional Record Online through the Government Publishing Office [<a href="https://www.gpo.gov">www.gpo.gov</a>]By Mr. MURPHY of North Carolina:H.R. 3428.Congress has the power to enact this legislation pursuantto the following:Article 1, Section 8 of the United States Constitution[Page H2654]</pre>]]>
    </constitutionalAuthorityStatementText>
    <committees>
      <item>
        <systemCode>hsag00</systemCode>
        <name>Agriculture Committee</name>
        <chamber>House</chamber>
        <type>Standing</type>
        <subcommittees>
          <item>
            <systemCode>hsag03</systemCode>
            <name>Nutrition, Oversight, and Department Operations Subcommittee</name>
            <activities>
              <item>
                <name>Referred to</name>
                <date>2021-07-01T19:31:18Z</date>
              </item>
            </activities>
          </item>
        </subcommittees>
        <activities>
          <item>
            <name>Referred to</name>
            <date>2021-05-20T13:00:36Z</date>
          </item>
        </activities>
      </item>
      <item>
        <systemCode>hsif00</systemCode>
        <name>Energy and Commerce Committee</name>
        <chamber>House</chamber>
        <type>Standing</type>
        <subcommittees>
          <item>
            <systemCode>hsif03</systemCode>
            <name>Energy Subcommittee</name>
            <activities>
              <item>
                <name>Referred to</name>
                <date>2021-05-21T18:18:27Z</date>
              </item>
            </activities>
          </item>
        </subcommittees>
        <activities>
          <item>
            <name>Referred to</name>
            <date>2021-05-20T13:00:46Z</date>
          </item>
        </activities>
      </item>
      <item>
        <systemCode>hsed00</systemCode>
        <name>Education and Labor Committee</name>
        <chamber>House</chamber>
        <type>Standing</type>
        <activities>
          <item>
            <name>Referred to</name>
            <date>2021-05-20T13:00:41Z</date>
          </item>
        </activities>
      </item>
    </committees>
    <actions>
      <item>
        <actionDate>2021-07-01</actionDate>
        <committees>
          <item>
            <systemCode>hsag03</systemCode>
            <name>Nutrition, Oversight, and Department Operations Subcommittee</name>
          </item>
        </committees>
        <sourceSystem>
          <code>1</code>
          <name>House committee actions</name>
        </sourceSystem>
        <text>Referred to the Subcommittee on Nutrition, Oversight, and Department Operations.</text>
        <type>Committee</type>
      </item>
      <item>
        <actionDate>2021-05-21</actionDate>
        <committees>
          <item>
            <systemCode>hsif03</systemCode>
            <name>Energy Subcommittee</name>
          </item>
        </committees>
        <sourceSystem>
          <code>1</code>
          <name>House committee actions</name>
        </sourceSystem>
        <text>Referred to the Subcommittee on Energy.</text>
        <type>Committee</type>
      </item>
      <item>
        <actionDate>2021-05-20</actionDate>
        <text>Referred to the Committee on Agriculture, and in addition to the Committees on Education and Labor, and Energy and Commerce, for a period to be subsequently determined by the Speaker, in each case for consideration of such provisions as fall within the jurisdiction of the committee concerned.</text>
        <type>IntroReferral</type>
        <actionCode>H11100</actionCode>
        <sourceSystem>
          <code>2</code>
          <name>House floor actions</name>
        </sourceSystem>
        <committees>
          <item>
            <systemCode>hsif00</systemCode>
            <name>Energy and Commerce Committee</name>
          </item>
        </committees>
      </item>
      <item>
        <actionDate>2021-05-20</actionDate>
        <text>Referred to the Committee on Agriculture, and in addition to the Committees on Education and Labor, and Energy and Commerce, for a period to be subsequently determined by the Speaker, in each case for consideration of such provisions as fall within the jurisdiction of the committee concerned.</text>
        <type>IntroReferral</type>
        <actionCode>H11100</actionCode>
        <sourceSystem>
          <code>2</code>
          <name>House floor actions</name>
        </sourceSystem>
        <committees>
          <item>
            <systemCode>hsed00</systemCode>
            <name>Education and Labor Committee</name>
          </item>
        </committees>
      </item>
      <item>
        <actionDate>2021-05-20</actionDate>
        <text>Referred to the Committee on Agriculture, and in addition to the Committees on Education and Labor, and Energy and Commerce, for a period to be subsequently determined by the Speaker, in each case for consideration of such provisions as fall within the jurisdiction of the committee concerned.</text>
        <type>IntroReferral</type>
        <actionCode>H11100</actionCode>
        <sourceSystem>
          <code>2</code>
          <name>House floor actions</name>
        </sourceSystem>
        <committees>
          <item>
            <systemCode>hsag00</systemCode>
            <name>Agriculture Committee</name>
          </item>
        </committees>
      </item>
      <item>
        <actionDate>2021-05-20</actionDate>
        <text>Introduced in House</text>
        <type>IntroReferral</type>
        <actionCode>Intro-H</actionCode>
        <sourceSystem>
          <code>9</code>
          <name>Library of Congress</name>
        </sourceSystem>
      </item>
      <item>
        <actionDate>2021-05-20</actionDate>
        <text>Introduced in House</text>
        <type>IntroReferral</type>
        <actionCode>1000</actionCode>
        <sourceSystem>
          <code>9</code>
          <name>Library of Congress</name>
        </sourceSystem>
      </item>
    </actions>
    <sponsors>
      <item>
        <bioguideId>M001210</bioguideId>
        <fullName>Rep. Murphy, Gregory [R-NC-3]</fullName>
        <firstName>Gregory</firstName>
        <lastName>Murphy</lastName>
        <party>R</party>
        <state>NC</state>
        <identifiers>
          <bioguideId>M001210</bioguideId>
        </identifiers>
        <district>3</district>
        <isByRequest>N</isByRequest>
      </item>
    </sponsors>
    <cosponsors>
      <item>
        <bioguideId>W000814</bioguideId>
        <fullName>Rep. Weber, Randy K., Sr. [R-TX-14]</fullName>
        <firstName>Randy</firstName>
        <lastName>Weber</lastName>
        <party>R</party>
        <state>TX</state>
        <identifiers>
          <bioguideId>W000814</bioguideId>
        </identifiers>
        <middleName>K.</middleName>
        <district>14</district>
        <sponsorshipDate>2021-05-20</sponsorshipDate>
        <isOriginalCosponsor>True</isOriginalCosponsor>
      </item>
      <item>
        <bioguideId>H001082</bioguideId>
        <fullName>Rep. Hern, Kevin [R-OK-1]</fullName>
        <firstName>Kevin</firstName>
        <lastName>Hern</lastName>
        <party>R</party>
        <state>OK</state>
        <identifiers>
          <bioguideId>H001082</bioguideId>
        </identifiers>
        <district>1</district>
        <sponsorshipDate>2021-05-20</sponsorshipDate>
        <isOriginalCosponsor>True</isOriginalCosponsor>
      </item>
      <item>
        <bioguideId>N000190</bioguideId>
        <fullName>Rep. Norman, Ralph [R-SC-5]</fullName>
        <firstName>Ralph</firstName>
        <lastName>Norman</lastName>
        <party>R</party>
        <state>SC</state>
        <identifiers>
          <bioguideId>N000190</bioguideId>
        </identifiers>
        <district>5</district>
        <sponsorshipDate>2021-05-20</sponsorshipDate>
        <isOriginalCosponsor>True</isOriginalCosponsor>
      </item>
      <item>
        <bioguideId>P000605</bioguideId>
        <fullName>Rep. Perry, Scott [R-PA-10]</fullName>
        <firstName>Scott</firstName>
        <lastName>Perry</lastName>
        <party>R</party>
        <state>PA</state>
        <identifiers>
          <bioguideId>P000605</bioguideId>
        </identifiers>
        <district>10</district>
        <sponsorshipDate>2021-05-20</sponsorshipDate>
        <isOriginalCosponsor>True</isOriginalCosponsor>
      </item>
      <item>
        <bioguideId>R000603</bioguideId>
        <fullName>Rep. Rouzer, David [R-NC-7]</fullName>
        <firstName>David</firstName>
        <lastName>Rouzer</lastName>
        <party>R</party>
        <state>NC</state>
        <identifiers>
          <bioguideId>R000603</bioguideId>
        </identifiers>
        <district>7</district>
        <sponsorshipDate>2021-05-20</sponsorshipDate>
        <isOriginalCosponsor>True</isOriginalCosponsor>
      </item>
      <item>
        <bioguideId>C001039</bioguideId>
        <fullName>Rep. Cammack, Kat [R-FL-3]</fullName>
        <firstName>Kat</firstName>
        <lastName>Cammack</lastName>
        <party>R</party>
        <state>FL</state>
        <identifiers>
          <bioguideId>C001039</bioguideId>
        </identifiers>
        <district>3</district>
        <sponsorshipDate>2021-05-25</sponsorshipDate>
        <isOriginalCosponsor>False</isOriginalCosponsor>
      </item>
      <item>
        <bioguideId>H001072</bioguideId>
        <fullName>Rep. Hill, J. French [R-AR-2]</fullName>
        <firstName>J.</firstName>
        <lastName>Hill</lastName>
        <party>R</party>
        <state>AR</state>
        <identifiers>
          <bioguideId>H001072</bioguideId>
        </identifiers>
        <middleName>French</middleName>
        <district>2</district>
        <sponsorshipDate>2021-05-28</sponsorshipDate>
        <isOriginalCosponsor>False</isOriginalCosponsor>
      </item>
    </cosponsors>
    <policyArea>
      <name>Agriculture and Food</name>
    </policyArea>
    <subjects>
      <legislativeSubjects/>
      <policyArea>
        <name>Agriculture and Food</name>
      </policyArea>
    </subjects>
    <summaries>
      <summary>
        <versionCode>00</versionCode>
        <actionDate>2021-05-20</actionDate>
        <actionDesc>Introduced in House</actionDesc>
        <updateDate>2022-08-17T13:05:55Z</updateDate>
        <text>
          <![CDATA[ <p><b>SNAP Reform Act of 2021</b></p> <p>This bill modifies eligibility under the Supplemental Nutrition Assistance Program (SNAP) with respect to individuals who receive other forms of assistance. </p> <p>Currently, households may be considered categorically eligible for SNAP if all members receive certain other assistance, such as under the Temporary Assistance for Needy Families (TANF) program. The bill specifies that members receiving TANF assistance must (1) receive at least $150 a month in cash assistance under TANF for an extended period with an income of up to 130% of the federal poverty level (FPL), or (2) be elderly or disabled and receive cash assistance or ongoing and substantial services under TANF with an income of up to 200% of the FPL.</p> <p>The bill also increases the maximum allowable resources for SNAP eligibility and specifies that certain allowances relating to energy assistance extend only to households with elderly members.</p>]]>
        </text>
      </summary>
    </summaries>
    <title>SNAP Reform Act of 2021</title>
    <titles>
      <item>
        <titleType>Display Title</titleType>
        <title>SNAP Reform Act of 2021</title>
      </item>
      <item>
        <titleType>Official Title as Introduced</titleType>
        <title>To strengthen the supplemental nutrition assistance program (SNAP) categorical eligibility for applicants who already receive supplemental assistance elsewhere and for those with assets high enough to not require assistance, and for other purposes.</title>
        <billTextVersionName>Introduced in House</billTextVersionName>
        <billTextVersionCode>IH</billTextVersionCode>
      </item>
      <item>
        <titleType>Short Title(s) as Introduced</titleType>
        <title>SNAP Reform Act of 2021</title>
        <billTextVersionName>Introduced in House</billTextVersionName>
        <billTextVersionCode>IH</billTextVersionCode>
      </item>
    </titles>
    <textVersions>
      <item>
        <type>Introduced in House</type>
        <date>2021-05-20T04:00:00Z</date>
        <formats>
          <item>
            <url>https://www.govinfo.gov/content/pkg/BILLS-117hr3428ih/xml/BILLS-117hr3428ih.xml</url>
          </item>
        </formats>
      </item>
      <item>
        <date/>
        <formats/>
        <type/>
      </item>
    </textVersions>
    <latestAction>
      <actionDate>2021-07-01</actionDate>
      <text>Referred to the Subcommittee on Nutrition, Oversight, and Department Operations.</text>
    </latestAction>
  </bill>
  <dublinCore xmlns:dc="http://purl.org/dc/elements/1.1/">
    <dc:format>text/xml</dc:format>
    <dc:language>EN</dc:language>
    <dc:rights>Pursuant to Title 17 Section 105 of the United States Code, this file is not subject to copyright protection and is in the public domain.</dc:rights>
    <dc:contributor>Congressional Research Service, Library of Congress</dc:contributor>
    <dc:description>This file contains bill summaries and statuses for federal legislation. A bill summary describes the most significant provisions of a piece of legislation and details the effects the legislative text may have on current law and federal programs. Bill summaries are authored by the Congressional Research Service (CRS) of the Library of Congress. As stated in Public Law 91-510 (2 USC 166 (d)(6)), one of the duties of CRS is "to prepare summaries and digests of bills and resolutions of a public general nature introduced in the Senate or House of Representatives". For more information, refer to the User Guide that accompanies this file.</dc:description>
  </dublinCore>
</billStatus>
